gateway/__init__.py
gateway/advanced.py
gateway/approximation_store.py
gateway/confidence_evaluator.py
gateway/prediction_engine.py
gateway/refinement_worker.py
gateway/server.py
gateway/advanced/__init__.py
gateway/advanced/advanced_prediction_engine.py
gateway/advanced/formal_error_bounds.py
gateway/advanced/stale_on_error_resilience.py
latencyzero/__init__.py
latencyzero/client.py
latencyzero/config.py
latencyzero/decorator.py
latencyzero/error_messages.py
latencyzero-0.1.1.dist-info/METADATA
latencyzero-0.1.1.dist-info/WHEEL
latencyzero-0.1.1.dist-info/top_level.txt
latencyzero-0.1.1.dist-info/RECORD
